ckanext_multiuploadform-1.3.3-py3.13-nspkg.pth
ckanext/multiuploadform/__init__.py
ckanext/multiuploadform/controllers.py
ckanext/multiuploadform/lib.py
ckanext/multiuploadform/plugin.py
ckanext/multiuploadform/views.py
ckanext/multiuploadform/assets/drag_drop.js
ckanext/multiuploadform/assets/multi_uploader.css
ckanext/multiuploadform/assets/multi_uploader.js
ckanext/multiuploadform/assets/webassets.yml
ckanext/multiuploadform/i18n/de/LC_MESSAGES/ckanext-multiuploadform.mo
ckanext/multiuploadform/templates/multiuploadform/snippets/multiupload_form.html
ckanext/multiuploadform/templates/multiuploadform/snippets/progress_bar_modal.html
ckanext/multiuploadform/templates/package/new_resource.html
ckanext/multiuploadform/templates/package/new_resource_not_draft.html
ckanext/multiuploadform/tests/__init__.py
ckanext/multiuploadform/tests/test_multiuploader.py
ckanext_multiuploadform-1.3.3.dist-info/licenses/LICENSE
ckanext_multiuploadform-1.3.3.dist-info/METADATA
ckanext_multiuploadform-1.3.3.dist-info/WHEEL
ckanext_multiuploadform-1.3.3.dist-info/entry_points.txt
ckanext_multiuploadform-1.3.3.dist-info/namespace_packages.txt
ckanext_multiuploadform-1.3.3.dist-info/top_level.txt
ckanext_multiuploadform-1.3.3.dist-info/RECORD
